equation/__init__.py
equation/quadratic_equation.py
test/__init__.py
test/quadratic_quation_test.py
equation_solver-1.0.0.dist-info/LICENSE
equation_solver-1.0.0.dist-info/METADATA
equation_solver-1.0.0.dist-info/WHEEL
equation_solver-1.0.0.dist-info/top_level.txt
equation_solver-1.0.0.dist-info/RECORD
