Metadata-Version: 2.1
Name: equation-solver
Version: 1.0.0
Summary: A Quadratic Equation Solver package
Home-page: https://github.com/AbhimanyuHK/QuadraticEquationSolver
Author: Abhimanyu HK
Author-email: manyu1994@hotmail.com
License: UNKNOWN
Platform: UNKNOWN
Classifier: Programming Language :: Python :: 3
Classifier: License :: OSI Approved :: MIT License
Classifier: Operating System :: OS Independent
